Metadata-Version: 2.1
Name: py-readability-metrics-small
Version: 1.7
Summary: Score text "Readability" with popular formulas and metrics including Flesch-Kincaid, Gunning Fog, ARI, Dale Chall, SMOG, Spache and more
Home-page: https://github.com/ben-gray-dev/py-readability-metrics-small
Author: Ben Gray
Author-email: bgray27613@gmail.com
License: MIT
Keywords: readability metrics text difficulty grade level
Classifier: Programming Language :: Python :: 3
Classifier: License :: OSI Approved :: MIT License
Classifier: Operating System :: OS Independent
License-File: LICENSE
Requires-Dist: nltk
